video_image_watermark_mcp/__init__.py
video_image_watermark_mcp/main.py
mcpcn_video_image_watermark_mcp-0.1.4.dist-info/METADATA
mcpcn_video_image_watermark_mcp-0.1.4.dist-info/WHEEL
mcpcn_video_image_watermark_mcp-0.1.4.dist-info/entry_points.txt
mcpcn_video_image_watermark_mcp-0.1.4.dist-info/RECORD
